yall/__init__.py
yall-0.0.2.dist-info/LICENSE
yall-0.0.2.dist-info/METADATA
yall-0.0.2.dist-info/WHEEL
yall-0.0.2.dist-info/top_level.txt
yall-0.0.2.dist-info/RECORD
